{
  "artist": "Dj Guuga",
  "artistId": "1cNPXWhKfjI0fT5EMCnamR",
  "songs": [
    {
      "artist": "Dj Guuga",
      "artistId": "1cNPXWhKfjI0fT5EMCnamR",
      "trackName": "Vidrado Em Você",
      "trackId": "1HJU78CRk4vxvjE5Cs1BCt",
      "total": 236684283,
      "daily": 983832
    },
    {
      "artist": "Dj Guuga",
      "artistId": "1cNPXWhKfjI0fT5EMCnamR",
      "trackName": "Volta Bebê, Volta Neném",
      "trackId": "4wQUopWk9Ed7Ng5qpKN5qd",
      "total": 132013589,
      "daily": 7827
    },
    {
      "artist": "Dj Guuga",
      "artistId": "1cNPXWhKfjI0fT5EMCnamR",
      "trackName": "Depende",
      "trackId": "0sTEUNuhl7f77EqolDIPh7",
      "total": 106980661,
      "daily": 10592
    },
    {
      "artist": "Dj Guuga",
      "artistId": "1cNPXWhKfjI0fT5EMCnamR",
      "trackName": "Helicóptero",
      "trackId": "1f2ETfkMwP1wvXgl4vvAlX",
      "total": 55155880,
      "daily": 72360
    },
    {
      "artist": "Dj Guuga",
      "artistId": "1cNPXWhKfjI0fT5EMCnamR",
      "trackName": "Vem Pro Cabaré",
      "trackId": "4RGAAOXqqJGr7U60W4Agqg",
      "total": 52548611,
      "daily": 23900
    },
    {
      "artist": "Dj Guuga",
      "artistId": "1cNPXWhKfjI0fT5EMCnamR",
      "trackName": "Intenso boom boom ( Acompanha o Grave )",
      "trackId": "5izDMFw5DIJsRb8wEukIYK",
      "total": 49135413,
      "daily": 48329
    },
    {
      "artist": "Dj Guuga",
      "artistId": "1cNPXWhKfjI0fT5EMCnamR",
      "trackName": "Funk do Pai",
      "trackId": "2y0R8K8qXgo7kQzyiZgWjV",
      "total": 31847899,
      "daily": 3858
    },
    {
      "artist": "Dj Guuga",
      "artistId": "1cNPXWhKfjI0fT5EMCnamR",
      "trackName": "Ta Apaixonado Babaca",
      "trackId": "7N3BrHFlnZbOs8lPGPg1gg",
      "total": 30720709,
      "daily": 3342
    },
    {
      "artist": "Dj Guuga",
      "artistId": "1cNPXWhKfjI0fT5EMCnamR",
      "trackName": "Castigando",
      "trackId": "5wSfNKAbyYvovcplF45i4Z",
      "total": 30271412,
      "daily": 11802
    },
    {
      "artist": "Dj Guuga",
      "artistId": "1cNPXWhKfjI0fT5EMCnamR",
      "trackName": "Os Penetra",
      "trackId": "79gy4jbNEfqWfBGaIEmXJ8",
      "total": 27966606,
      "daily": 25871
    },
    {
      "artist": "Dj Guuga",
      "artistId": "1cNPXWhKfjI0fT5EMCnamR",
      "trackName": "Disputa Pra Qual Mais Kika",
      "trackId": "0CcslvuRobsWDZ5jNuWm3q",
      "total": 26585163,
      "daily": 10819
    },
    {
      "artist": "Dj Guuga",
      "artistId": "1cNPXWhKfjI0fT5EMCnamR",
      "trackName": "Saudade do Seu Love",
      "trackId": "7Kg1ukDe5T7olD4Jopvdvr",
      "total": 24885811,
      "daily": 14195
    },
    {
      "artist": "Dj Guuga",
      "artistId": "1cNPXWhKfjI0fT5EMCnamR",
      "trackName": "7 Dias 7 Corpos",
      "trackId": "3nbdrAJtl3Qkx7RTsNqRsQ",
      "total": 21899991,
      "daily": 1882
    },
    {
      "artist": "Dj Guuga",
      "artistId": "1cNPXWhKfjI0fT5EMCnamR",
      "trackName": "Oh My God",
      "trackId": "0lxmZ4evzbuphwYIj8Kqr0",
      "total": 21774917,
      "daily": 3549
    },
    {
      "artist": "Dj Guuga",
      "artistId": "1cNPXWhKfjI0fT5EMCnamR",
      "trackName": "Sexta Meu Celular Fica Sem Sinal",
      "trackId": "0KEQ21N1eQGZ6fjHTKqwZH",
      "total": 21518379,
      "daily": 7440
    },
    {
      "artist": "Dj Guuga",
      "artistId": "1cNPXWhKfjI0fT5EMCnamR",
      "trackName": "Fez assim Fiu Fiu",
      "trackId": "5kQbJGUo6PdlwngBV7sjsF",
      "total": 21237354,
      "daily": 24814
    },
    {
      "artist": "Dj Guuga",
      "artistId": "1cNPXWhKfjI0fT5EMCnamR",
      "trackName": "Petulância",
      "trackId": "19pMuuPrQBO2PwGyNC7W26",
      "total": 20611726,
      "daily": 7037
    },
    {
      "artist": "Dj Guuga",
      "artistId": "1cNPXWhKfjI0fT5EMCnamR",
      "trackName": "É Tchau Pra Quem Namora",
      "trackId": "5x3Pyt9muvNIv29XH0M9Bm",
      "total": 18727077,
      "daily": 6235
    },
    {
      "artist": "Dj Guuga",
      "artistId": "1cNPXWhKfjI0fT5EMCnamR",
      "trackName": "Depende",
      "trackId": "2OsPujKDKv0PgbfsMHtU7m",
      "total": 18165366,
      "daily": 1635
    },
    {
      "artist": "Dj Guuga",
      "artistId": "1cNPXWhKfjI0fT5EMCnamR",
      "trackName": "Os 4 Cara Que a Bandida Se Amarra",
      "trackId": "5NsVmGp081xzIQjUca5oz6",
      "total": 14006106,
      "daily": 1007
    },
    {
      "artist": "Dj Guuga",
      "artistId": "1cNPXWhKfjI0fT5EMCnamR",
      "trackName": "Senta pra Carai",
      "trackId": "2ZsXVcdmyIHalyqoNdCB7m",
      "total": 13671150,
      "daily": 523
    },
    {
      "artist": "Dj Guuga",
      "artistId": "1cNPXWhKfjI0fT5EMCnamR",
      "trackName": "O Golpe tá aí Cai Quem Quer",
      "trackId": "5kZCL0ezvt1EEDyPojBPWH",
      "total": 13016928,
      "daily": 1761
    },
    {
      "artist": "Dj Guuga",
      "artistId": "1cNPXWhKfjI0fT5EMCnamR",
      "trackName": "Casamento",
      "trackId": "6ADti3GRke23m1CWZH3aPZ",
      "total": 10637476,
      "daily": 7775
    },
    {
      "artist": "Dj Guuga",
      "artistId": "1cNPXWhKfjI0fT5EMCnamR",
      "trackName": "Não Perde Tempo",
      "trackId": "4f2VntnFwBYtuYkROXEyTp",
      "total": 9625775,
      "daily": 1026
    },
    {
      "artist": "Dj Guuga",
      "artistId": "1cNPXWhKfjI0fT5EMCnamR",
      "trackName": "Arrocha Dos Cornos",
      "trackId": "443HOlFVAfzqcn5teJQ6el",
      "total": 9273623,
      "daily": 3823
    },
    {
      "artist": "Dj Guuga",
      "artistId": "1cNPXWhKfjI0fT5EMCnamR",
      "trackName": "Helicóptero 2",
      "trackId": "4uxdj8If9ky0WWuX6TyK2y",
      "total": 8608422,
      "daily": 11022
    },
    {
      "artist": "Dj Guuga",
      "artistId": "1cNPXWhKfjI0fT5EMCnamR",
      "trackName": "Acabou Você Não Deu Valor",
      "trackId": "7DGarr74rOLkP45Pn5xINs",
      "total": 7811263,
      "daily": 3275
    },
    {
      "artist": "Dj Guuga",
      "artistId": "1cNPXWhKfjI0fT5EMCnamR",
      "trackName": "Vou Ver a Forma de Enrolar Você",
      "trackId": "6zNz8v5yEWOZvvnGA7H2Ph",
      "total": 7757898,
      "daily": 596
    },
    {
      "artist": "Dj Guuga",
      "artistId": "1cNPXWhKfjI0fT5EMCnamR",
      "trackName": "Sai da Frente Lá Vem Elas",
      "trackId": "7Lp3VS47MXYq2KyHKGs9u4",
      "total": 7737450,
      "daily": 733
    },
    {
      "artist": "Dj Guuga",
      "artistId": "1cNPXWhKfjI0fT5EMCnamR",
      "trackName": "Vou Te Bloquear",
      "trackId": "4G2nweYrY5oBkArp5UgIdz",
      "total": 7396873,
      "daily": 154
    },
    {
      "artist": "Dj Guuga",
      "artistId": "1cNPXWhKfjI0fT5EMCnamR",
      "trackName": "Agora Chora",
      "trackId": "49MreHnSx9qFku1nyZxKX8",
      "total": 7360476,
      "daily": 3946
    },
    {
      "artist": "Dj Guuga",
      "artistId": "1cNPXWhKfjI0fT5EMCnamR",
      "trackName": "Só Vamo",
      "trackId": "2P9f72B0DaYEv0E4ZIF3m9",
      "total": 7348290,
      "daily": 5134
    },
    {
      "artist": "Dj Guuga",
      "artistId": "1cNPXWhKfjI0fT5EMCnamR",
      "trackName": "No Escurinho",
      "trackId": "2gowXETWL6ATUu7xIF0IMI",
      "total": 7158728,
      "daily": 549
    },
    {
      "artist": "Dj Guuga",
      "artistId": "1cNPXWhKfjI0fT5EMCnamR",
      "trackName": "Quem Perdeu Corre Atrás Até Hoje",
      "trackId": "6hAblwlfoR7Dj9Ov7NsWUr",
      "total": 7044443,
      "daily": 3541
    },
    {
      "artist": "Dj Guuga",
      "artistId": "1cNPXWhKfjI0fT5EMCnamR",
      "trackName": "Idiota",
      "trackId": "4lYuoPn9AIl10NL9vZUN9v",
      "total": 6860843,
      "daily": 982
    },
    {
      "artist": "Dj Guuga",
      "artistId": "1cNPXWhKfjI0fT5EMCnamR",
      "trackName": "Voltei Avisa Lá, Avisa Lá",
      "trackId": "4eUZ6ItTbvwtxPyOqsyIee",
      "total": 6792522,
      "daily": 7848
    },
    {
      "artist": "Dj Guuga",
      "artistId": "1cNPXWhKfjI0fT5EMCnamR",
      "trackName": "Quanta Abundância",
      "trackId": "2Bgu0HEludoeE7XJntrOR2",
      "total": 6727759,
      "daily": 1411
    },
    {
      "artist": "Dj Guuga",
      "artistId": "1cNPXWhKfjI0fT5EMCnamR",
      "trackName": "Chama Eu",
      "trackId": "4Tg0t6WLMGEBTVTIvVrPYp",
      "total": 6606669,
      "daily": 622
    },
    {
      "artist": "Dj Guuga",
      "artistId": "1cNPXWhKfjI0fT5EMCnamR",
      "trackName": "A Fila Querendo tá no Seu Lugar",
      "trackId": "3Nn6tog2YGtht7MHKuZc2b",
      "total": 6600940,
      "daily": 8573
    },
    {
      "artist": "Dj Guuga",
      "artistId": "1cNPXWhKfjI0fT5EMCnamR",
      "trackName": "Melhor Rolê da City - Ao Vivo",
      "trackId": "7e6Gh17UPn9ykTSmrxlXga",
      "total": 6253699,
      "daily": 244
    },
    {
      "artist": "Dj Guuga",
      "artistId": "1cNPXWhKfjI0fT5EMCnamR",
      "trackName": "Promete Que Senta Gostoso",
      "trackId": "1IedOHgU4hRiOz3llO7Tsf",
      "total": 6125875,
      "daily": 2497
    },
    {
      "artist": "Dj Guuga",
      "artistId": "1cNPXWhKfjI0fT5EMCnamR",
      "trackName": "Elas Tão Pedindo Obrigado",
      "trackId": "4e2ky9BSgpZhXU7p96iA6R",
      "total": 5889558,
      "daily": 665
    },
    {
      "artist": "Dj Guuga",
      "artistId": "1cNPXWhKfjI0fT5EMCnamR",
      "trackName": "Latinha",
      "trackId": "29swF6QIfZbrrhrWhFINzO",
      "total": 5864642,
      "daily": 995
    },
    {
      "artist": "Dj Guuga",
      "artistId": "1cNPXWhKfjI0fT5EMCnamR",
      "trackName": "Eletro Funk - Na Onda do Berimbau",
      "trackId": "0FQ0oy68DWEbyEanrY87FG",
      "total": 5034661,
      "daily": 1148
    },
    {
      "artist": "Dj Guuga",
      "artistId": "1cNPXWhKfjI0fT5EMCnamR",
      "trackName": "Duelo de Bumbum",
      "trackId": "4fvqb7gpjL6xH0OkDPCEN7",
      "total": 4963991,
      "daily": 2656
    },
    {
      "artist": "Dj Guuga",
      "artistId": "1cNPXWhKfjI0fT5EMCnamR",
      "trackName": "Vidrado em Você - Slowed",
      "trackId": "7y5nIIO6algo0DogywjRnD",
      "total": 4921556,
      "daily": 52837
    },
    {
      "artist": "Dj Guuga",
      "artistId": "1cNPXWhKfjI0fT5EMCnamR",
      "trackName": "Vou Ficar Doidão",
      "trackId": "6CzqVMcBjTHwFsGKtBBKWK",
      "total": 4891399,
      "daily": 422
    },
    {
      "artist": "Dj Guuga",
      "artistId": "1cNPXWhKfjI0fT5EMCnamR",
      "trackName": "Me Chamou de Vida",
      "trackId": "1S8gv25mvCAmzJy5IFo0H1",
      "total": 4865379,
      "daily": 1035
    },
    {
      "artist": "Dj Guuga",
      "artistId": "1cNPXWhKfjI0fT5EMCnamR",
      "trackName": "Disputa vs Duelo",
      "trackId": "1yFMVLCW4OpZPBjfLMhA7j",
      "total": 4860253,
      "daily": 3685
    },
    {
      "artist": "Dj Guuga",
      "artistId": "1cNPXWhKfjI0fT5EMCnamR",
      "trackName": "Que Bonde É Esse",
      "trackId": "4DmisKVXaXtRfM9ewjvo1G",
      "total": 4796414,
      "daily": 746
    },
    {
      "artist": "Dj Guuga",
      "artistId": "1cNPXWhKfjI0fT5EMCnamR",
      "trackName": "Putaria Pra Coroa",
      "trackId": "0iu0fKH1sJx2GH0KgOgVTG",
      "total": 4442016,
      "daily": 1121
    },
    {
      "artist": "Dj Guuga",
      "artistId": "1cNPXWhKfjI0fT5EMCnamR",
      "trackName": "Sem Cumprimentar",
      "trackId": "6Xt16YvPI36XAxc2Ft9P5i",
      "total": 4348823,
      "daily": 383
    },
    {
      "artist": "Dj Guuga",
      "artistId": "1cNPXWhKfjI0fT5EMCnamR",
      "trackName": "Chama No Probleminha",
      "trackId": "1ZRZbAAAzAYHbCiGhVGB1x",
      "total": 4122180,
      "daily": 790
    },
    {
      "artist": "Dj Guuga",
      "artistId": "1cNPXWhKfjI0fT5EMCnamR",
      "trackName": "Melhor Amigo da Sua Vida",
      "trackId": "187kJciTz8F45IjS1qOnjE",
      "total": 3896186,
      "daily": 1670
    },
    {
      "artist": "Dj Guuga",
      "artistId": "1cNPXWhKfjI0fT5EMCnamR",
      "trackName": "Bum Bum Batendo",
      "trackId": "3O07nyzUNjfIZ37dF66yQY",
      "total": 3786822,
      "daily": 464
    },
    {
      "artist": "Dj Guuga",
      "artistId": "1cNPXWhKfjI0fT5EMCnamR",
      "trackName": "Me Chama de Amor, Pede Com Carinho",
      "trackId": "7qOKyJzw08rEKQfI8YkeBh",
      "total": 3586345,
      "daily": 1046
    },
    {
      "artist": "Dj Guuga",
      "artistId": "1cNPXWhKfjI0fT5EMCnamR",
      "trackName": "Pressão",
      "trackId": "2JDHeoLNbIRlJsZI4krVfP",
      "total": 3500553,
      "daily": 2158
    },
    {
      "artist": "Dj Guuga",
      "artistId": "1cNPXWhKfjI0fT5EMCnamR",
      "trackName": "Filha do Sultão",
      "trackId": "144TUSYFO06ZU6SWASaTh6",
      "total": 3219352,
      "daily": 608
    },
    {
      "artist": "Dj Guuga",
      "artistId": "1cNPXWhKfjI0fT5EMCnamR",
      "trackName": "Bunda no Chão",
      "trackId": "1CmPFEbTz0SHVOwAoztEqH",
      "total": 3197516,
      "daily": 605
    },
    {
      "artist": "Dj Guuga",
      "artistId": "1cNPXWhKfjI0fT5EMCnamR",
      "trackName": "Chama As Amiga da Surfistinha",
      "trackId": "0NEoor0kBJF8VqJaztQ5ny",
      "total": 3114328,
      "daily": 452
    },
    {
      "artist": "Dj Guuga",
      "artistId": "1cNPXWhKfjI0fT5EMCnamR",
      "trackName": "Vamos Falar de Amor",
      "trackId": "4ndeNge6oHhll4j7NvVZLV",
      "total": 2814924,
      "daily": 197
    },
    {
      "artist": "Dj Guuga",
      "artistId": "1cNPXWhKfjI0fT5EMCnamR",
      "trackName": "Tipo pandeiro",
      "trackId": "1jDClHA6E3hAGsAJ5p1Co2",
      "total": 2717166,
      "daily": 1430
    },
    {
      "artist": "Dj Guuga",
      "artistId": "1cNPXWhKfjI0fT5EMCnamR",
      "trackName": "Arrocha de Bandido",
      "trackId": "3BGExmdHCWoqkjexf91Cjx",
      "total": 2662999,
      "daily": 520
    },
    {
      "artist": "Dj Guuga",
      "artistId": "1cNPXWhKfjI0fT5EMCnamR",
      "trackName": "Dinheiro Na Mão Calcinha No Chão",
      "trackId": "4Z5RGOeCavS0zK1grF1SoD",
      "total": 2523364,
      "daily": 178
    },
    {
      "artist": "Dj Guuga",
      "artistId": "1cNPXWhKfjI0fT5EMCnamR",
      "trackName": "Rave Safadinha Cavalona",
      "trackId": "34FtsI8SUMORSwWgaTbgj9",
      "total": 2462122,
      "daily": 447
    },
    {
      "artist": "Dj Guuga",
      "artistId": "1cNPXWhKfjI0fT5EMCnamR",
      "trackName": "Festa do 3 por 1",
      "trackId": "3uKKr7vb8Cj9ZvUckXGX8G",
      "total": 2427957,
      "daily": 452
    },
    {
      "artist": "Dj Guuga",
      "artistId": "1cNPXWhKfjI0fT5EMCnamR",
      "trackName": "Reagiu Vapo",
      "trackId": "3HnjasurAkFIfjS3b2iFU8",
      "total": 2317006,
      "daily": 894
    },
    {
      "artist": "Dj Guuga",
      "artistId": "1cNPXWhKfjI0fT5EMCnamR",
      "trackName": "MEGA ELETRO FUNK - Last Night",
      "trackId": "47WoK5cvSuVCANU3DW53JD",
      "total": 2234717,
      "daily": 3679
    },
    {
      "artist": "Dj Guuga",
      "artistId": "1cNPXWhKfjI0fT5EMCnamR",
      "trackName": "3 X 1 (Eletrofunk)",
      "trackId": "2bUIN4hQGVcrlG9E9zXrct",
      "total": 2202683,
      "daily": 5189
    },
    {
      "artist": "Dj Guuga",
      "artistId": "1cNPXWhKfjI0fT5EMCnamR",
      "trackName": "Pião de Lancha",
      "trackId": "1JyuNMtldLVaxrh0YhEbQY",
      "total": 2132601,
      "daily": 90
    },
    {
      "artist": "Dj Guuga",
      "artistId": "1cNPXWhKfjI0fT5EMCnamR",
      "trackName": "Bombeiro",
      "trackId": "7hxgp11pbzBQHoabaMHTtk",
      "total": 2031362,
      "daily": 382
    },
    {
      "artist": "Dj Guuga",
      "artistId": "1cNPXWhKfjI0fT5EMCnamR",
      "trackName": "Senta Pro Vaqueiro - Ao Vivo",
      "trackId": "3Y3aeUCS09XsZeghhWgyio",
      "total": 1946877,
      "daily": 2706
    },
    {
      "artist": "Dj Guuga",
      "artistId": "1cNPXWhKfjI0fT5EMCnamR",
      "trackName": "Ele Foi Trocado Por Mulher",
      "trackId": "3fqnqYKh2KHAKuCB1qmn8H",
      "total": 1939065,
      "daily": 557
    },
    {
      "artist": "Dj Guuga",
      "artistId": "1cNPXWhKfjI0fT5EMCnamR",
      "trackName": "Sonho dos Boys a Mais Gostosa da Favela",
      "trackId": "2So5oGagVRbPZD8zrLaFmp",
      "total": 1914279,
      "daily": 299
    },
    {
      "artist": "Dj Guuga",
      "artistId": "1cNPXWhKfjI0fT5EMCnamR",
      "trackName": "Jato",
      "trackId": "5rLEzhKiig8HAnibVWRLhG",
      "total": 1555241,
      "daily": 185
    },
    {
      "artist": "Dj Guuga",
      "artistId": "1cNPXWhKfjI0fT5EMCnamR",
      "trackName": "Otário",
      "trackId": "582hsb2VxFrCbTPQOKxXSm",
      "total": 1546378,
      "daily": 972
    },
    {
      "artist": "Dj Guuga",
      "artistId": "1cNPXWhKfjI0fT5EMCnamR",
      "trackName": "Uber das Meninas",
      "trackId": "26aEXwNhJ1wdbuXyKY8CNE",
      "total": 1499706,
      "daily": 59
    },
    {
      "artist": "Dj Guuga",
      "artistId": "1cNPXWhKfjI0fT5EMCnamR",
      "trackName": "Mega Putaria Escraxada",
      "trackId": "3nFRF1KLMsZCaR0Ar4pOXG",
      "total": 1491867,
      "daily": 378
    },
    {
      "artist": "Dj Guuga",
      "artistId": "1cNPXWhKfjI0fT5EMCnamR",
      "trackName": "Ao Som do Drake",
      "trackId": "4Xw46on6brMsT6PUB3vvZU",
      "total": 1447993,
      "daily": 62
    },
    {
      "artist": "Dj Guuga",
      "artistId": "1cNPXWhKfjI0fT5EMCnamR",
      "trackName": "É o Chefe",
      "trackId": "18XpTWLb2ntLlqcFpBNZnY",
      "total": 1402745,
      "daily": 168
    },
    {
      "artist": "Dj Guuga",
      "artistId": "1cNPXWhKfjI0fT5EMCnamR",
      "trackName": "Senta Sem Amor - Ao Vivo",
      "trackId": "2VM90FVr6uETWq5JW87Psd",
      "total": 1375061,
      "daily": 82
    },
    {
      "artist": "Dj Guuga",
      "artistId": "1cNPXWhKfjI0fT5EMCnamR",
      "trackName": "Rave Dos Hits",
      "trackId": "6p8lVAncvDozOwMEbPYxm7",
      "total": 1285194,
      "daily": 390
    },
    {
      "artist": "Dj Guuga",
      "artistId": "1cNPXWhKfjI0fT5EMCnamR",
      "trackName": "Vizinho",
      "trackId": "4iAb3IQq8svuBcxgMFAWO8",
      "total": 1274890,
      "daily": 809
    },
    {
      "artist": "Dj Guuga",
      "artistId": "1cNPXWhKfjI0fT5EMCnamR",
      "trackName": "Eu Era Feliz e Não Sabia",
      "trackId": "66dq7NT8r9uJ1T3nSzAMeV",
      "total": 1268380,
      "daily": 142
    },
    {
      "artist": "Dj Guuga",
      "artistId": "1cNPXWhKfjI0fT5EMCnamR",
      "trackName": "Brota Na Scandallo",
      "trackId": "6Mrn6nox06WctEEHPwXe75",
      "total": 1238180,
      "daily": 331
    },
    {
      "artist": "Dj Guuga",
      "artistId": "1cNPXWhKfjI0fT5EMCnamR",
      "trackName": "PORSCHE (feat. MC Teteu)",
      "trackId": "3yvOOL4T9piAi2eSVFBtrV",
      "total": 1154946,
      "daily": 175
    },
    {
      "artist": "Dj Guuga",
      "artistId": "1cNPXWhKfjI0fT5EMCnamR",
      "trackName": "Da Uns Puxe No Lança da Uns Trago No Beck",
      "trackId": "7LZKrOMGRHVHqPFF1nUeYh",
      "total": 1148972,
      "daily": 122
    },
    {
      "artist": "Dj Guuga",
      "artistId": "1cNPXWhKfjI0fT5EMCnamR",
      "trackName": "Dia de Maldade, Casa de Laureta",
      "trackId": "7bHknmMuRJIv2eyfNOZNAt",
      "total": 1117785,
      "daily": 74
    },
    {
      "artist": "Dj Guuga",
      "artistId": "1cNPXWhKfjI0fT5EMCnamR",
      "trackName": "É Tudo Bandida",
      "trackId": "5yPbfGpF7KuOdZD4oQN5SE",
      "total": 1087948,
      "daily": 28
    },
    {
      "artist": "Dj Guuga",
      "artistId": "1cNPXWhKfjI0fT5EMCnamR",
      "trackName": "Tem Cabaré Essa Noite",
      "trackId": "47PncZ0nk255BRqluwEFTe",
      "total": 1074600,
      "daily": 45
    },
    {
      "artist": "Dj Guuga",
      "artistId": "1cNPXWhKfjI0fT5EMCnamR",
      "trackName": "SÓ SEQUENCIA DE TOMA",
      "trackId": "15NeNHPLmhsTKaztbwJGLu",
      "total": 1039720,
      "daily": 5442
    },
    {
      "artist": "Dj Guuga",
      "artistId": "1cNPXWhKfjI0fT5EMCnamR",
      "trackName": "Putaria Proibido para Menores",
      "trackId": "6sp5F3Qn2a4cUKYluWi7go",
      "total": 1033589,
      "daily": 222
    },
    {
      "artist": "Dj Guuga",
      "artistId": "1cNPXWhKfjI0fT5EMCnamR",
      "trackName": "Esquece que a Mamãe ta Estourada",
      "trackId": "7oCIo8Wa9Q2cj7bXwoWCyd",
      "total": 1023628,
      "daily": 107
    },
    {
      "artist": "Dj Guuga",
      "artistId": "1cNPXWhKfjI0fT5EMCnamR",
      "trackName": "Tu Se Garante",
      "trackId": "2NpC2zkYZ9lvR3xOQCZfiz",
      "total": 967906,
      "daily": 80
    },
    {
      "artist": "Dj Guuga",
      "artistId": "1cNPXWhKfjI0fT5EMCnamR",
      "trackName": "As Minas Mamando No Carro e Fudendo No Beco",
      "trackId": "5tdRMvQZPo5eOt8ZjovAzV",
      "total": 966337,
      "daily": 92
    },
    {
      "artist": "Dj Guuga",
      "artistId": "1cNPXWhKfjI0fT5EMCnamR",
      "trackName": "Uma Perereca Só Enjoa",
      "trackId": "2ogy70eM1lW5b8yqWkHo1K",
      "total": 966021,
      "daily": 24
    },
    {
      "artist": "Dj Guuga",
      "artistId": "1cNPXWhKfjI0fT5EMCnamR",
      "trackName": "Piranha Barata",
      "trackId": "3CZOWLvGbSMZkwN4I3tIHB",
      "total": 948152,
      "daily": 105
    },
    {
      "artist": "Dj Guuga",
      "artistId": "1cNPXWhKfjI0fT5EMCnamR",
      "trackName": "Não Se Apega",
      "trackId": "4e3SMGE0d6vQSRzOeqmeUc",
      "total": 945343,
      "daily": 19
    },
    {
      "artist": "Dj Guuga",
      "artistId": "1cNPXWhKfjI0fT5EMCnamR",
      "trackName": "Elas Tá Pedindo por Favor Pra Dar",
      "trackId": "0r1m6pb9JDEBQKRr8YlR3s",
      "total": 871459,
      "daily": 108
    },
    {
      "artist": "Dj Guuga",
      "artistId": "1cNPXWhKfjI0fT5EMCnamR",
      "trackName": "Ta Usando Outro pra Me Esquecer",
      "trackId": "5cmsDyanGLFH9jHZF1Xg0T",
      "total": 840556,
      "daily": 21
    },
    {
      "artist": "Dj Guuga",
      "artistId": "1cNPXWhKfjI0fT5EMCnamR",
      "trackName": "Só Contatinho Novo",
      "trackId": "0rZD9pZBBnRa805XwLDgBW",
      "total": 834051,
      "daily": 12
    },
    {
      "artist": "Dj Guuga",
      "artistId": "1cNPXWhKfjI0fT5EMCnamR",
      "trackName": "Muleque Mil Grau",
      "trackId": "5vBUY91eq60gxI9BAtj1ZM",
      "total": 829429,
      "daily": 23
    },
    {
      "artist": "Dj Guuga",
      "artistId": "1cNPXWhKfjI0fT5EMCnamR",
      "trackName": "Festa Boa",
      "trackId": "3YbdgVzzZReUOMMJzzt659",
      "total": 814908,
      "daily": 122
    },
    {
      "artist": "Dj Guuga",
      "artistId": "1cNPXWhKfjI0fT5EMCnamR",
      "trackName": "Aquele Momento",
      "trackId": "2xR24BWgiODDOzIUUbTr5C",
      "total": 809895,
      "daily": 61
    },
    {
      "artist": "Dj Guuga",
      "artistId": "1cNPXWhKfjI0fT5EMCnamR",
      "trackName": "Rave do Guuga",
      "trackId": "1WR5RQJKs8ZtRPgFnkw1a9",
      "total": 795537,
      "daily": 85
    },
    {
      "artist": "Dj Guuga",
      "artistId": "1cNPXWhKfjI0fT5EMCnamR",
      "trackName": "Troquei o Amor Pelo Cabaré",
      "trackId": "4gPyUdUi4ndF6GluPQeSFV",
      "total": 787955,
      "daily": 313
    },
    {
      "artist": "Dj Guuga",
      "artistId": "1cNPXWhKfjI0fT5EMCnamR",
      "trackName": "Ta Duro Dorme",
      "trackId": "2Yi4e1TUbgAcxCQIe45z3y",
      "total": 778433,
      "daily": 87
    },
    {
      "artist": "Dj Guuga",
      "artistId": "1cNPXWhKfjI0fT5EMCnamR",
      "trackName": "Chama Papai",
      "trackId": "0GAggbgUj1EsGopMu4DjoN",
      "total": 772004,
      "daily": 120
    },
    {
      "artist": "Dj Guuga",
      "artistId": "1cNPXWhKfjI0fT5EMCnamR",
      "trackName": "Rave do It To It",
      "trackId": "6X92ms9AXhuA7Em46lgQIr",
      "total": 769100,
      "daily": 592
    },
    {
      "artist": "Dj Guuga",
      "artistId": "1cNPXWhKfjI0fT5EMCnamR",
      "trackName": "Bikini Neon",
      "trackId": "1wAcldjDdXGZ3zgVMJWcqh",
      "total": 751758,
      "daily": 4598
    },
    {
      "artist": "Dj Guuga",
      "artistId": "1cNPXWhKfjI0fT5EMCnamR",
      "trackName": "Kaboom",
      "trackId": "5sTrPA8VD3LvZoI8PUKCR2",
      "total": 728644,
      "daily": 802
    },
    {
      "artist": "Dj Guuga",
      "artistId": "1cNPXWhKfjI0fT5EMCnamR",
      "trackName": "A Bia e a Bruna",
      "trackId": "5P0Mw4JtU9mb7yJniLkTyV",
      "total": 715020,
      "daily": 111
    },
    {
      "artist": "Dj Guuga",
      "artistId": "1cNPXWhKfjI0fT5EMCnamR",
      "trackName": "Que Isso Novinha",
      "trackId": "0NvmkKTJY8Cvepw1gfGiyl",
      "total": 698948,
      "daily": 15
    },
    {
      "artist": "Dj Guuga",
      "artistId": "1cNPXWhKfjI0fT5EMCnamR",
      "trackName": "3 Dias 3 Noites",
      "trackId": "6Bj8CdekC48q1rebJpJlgh",
      "total": 682310,
      "daily": 116
    },
    {
      "artist": "Dj Guuga",
      "artistId": "1cNPXWhKfjI0fT5EMCnamR",
      "trackName": "É Tchau pra Quem Namora",
      "trackId": "2BwQBNHLvLpap6tPIxBCFa",
      "total": 681707,
      "daily": 199
    },
    {
      "artist": "Dj Guuga",
      "artistId": "1cNPXWhKfjI0fT5EMCnamR",
      "trackName": "Só Você",
      "trackId": "3rM8YyhP36PrWCCZMKTH0E",
      "total": 659393,
      "daily": 141
    },
    {
      "artist": "Dj Guuga",
      "artistId": "1cNPXWhKfjI0fT5EMCnamR",
      "trackName": "Japão",
      "trackId": "76ig9PWDw17fflhK4lrrhf",
      "total": 654068,
      "daily": 101
    },
    {
      "artist": "Dj Guuga",
      "artistId": "1cNPXWhKfjI0fT5EMCnamR",
      "trackName": "Cafetina e o Cafetão",
      "trackId": "4K5bF4dvSzHJQ6zBC4kZRz",
      "total": 619574,
      "daily": 84
    },
    {
      "artist": "Dj Guuga",
      "artistId": "1cNPXWhKfjI0fT5EMCnamR",
      "trackName": "Vai Maldita vs Toma Tapa Na Cara",
      "trackId": "3C0hCTfcdGuwi3kViZGOmu",
      "total": 613223,
      "daily": 46
    },
    {
      "artist": "Dj Guuga",
      "artistId": "1cNPXWhKfjI0fT5EMCnamR",
      "trackName": "Desce No Calcanhar",
      "trackId": "1YKRG8D3iKQ5pg0Jb9GxKJ",
      "total": 600393,
      "daily": 30
    },
    {
      "artist": "Dj Guuga",
      "artistId": "1cNPXWhKfjI0fT5EMCnamR",
      "trackName": "A Fila Anda a Catraca Gira",
      "trackId": "1K3MXcn8ijID2eYpUdnSDk",
      "total": 577001,
      "daily": 374
    },
    {
      "artist": "Dj Guuga",
      "artistId": "1cNPXWhKfjI0fT5EMCnamR",
      "trackName": "Flat do Pai - Ao Vivo",
      "trackId": "4j3D3kdXSKDY8AUsDX3Sur",
      "total": 556902,
      "daily": 48
    },
    {
      "artist": "Dj Guuga",
      "artistId": "1cNPXWhKfjI0fT5EMCnamR",
      "trackName": "Vai Ser Só Cachorrada",
      "trackId": "6chQCsV1HFlM2eeEuHN3fT",
      "total": 549408,
      "daily": 61
    },
    {
      "artist": "Dj Guuga",
      "artistId": "1cNPXWhKfjI0fT5EMCnamR",
      "trackName": "Acordou Gostosa Hoje",
      "trackId": "0aO1C6kQWNEu7k7g2pupD6",
      "total": 548544,
      "daily": 95
    },
    {
      "artist": "Dj Guuga",
      "artistId": "1cNPXWhKfjI0fT5EMCnamR",
      "trackName": "Faz um Pix pra Mim",
      "trackId": "4t5hSH3Zy57ZqQpcISY9pI",
      "total": 547896,
      "daily": 14
    },
    {
      "artist": "Dj Guuga",
      "artistId": "1cNPXWhKfjI0fT5EMCnamR",
      "trackName": "Vidrado em Você (Speed)",
      "trackId": "2C29v5jW6pXrcYzZt2FOxa",
      "total": 523974,
      "daily": 3657
    },
    {
      "artist": "Dj Guuga",
      "artistId": "1cNPXWhKfjI0fT5EMCnamR",
      "trackName": "Toda Impinadinha",
      "trackId": "2vXlkxz904KRGrv6BihE2R",
      "total": 518879,
      "daily": 6
    },
    {
      "artist": "Dj Guuga",
      "artistId": "1cNPXWhKfjI0fT5EMCnamR",
      "trackName": "Desce Vai no Chão",
      "trackId": "2HUVcKjMVIlSaAdUyoFwBM",
      "total": 514980,
      "daily": 206
    },
    {
      "artist": "Dj Guuga",
      "artistId": "1cNPXWhKfjI0fT5EMCnamR",
      "trackName": "Sua Nota É 10",
      "trackId": "369iGEoL9J6V1Z8mW0XGfZ",
      "total": 507405,
      "daily": 12
    },
    {
      "artist": "Dj Guuga",
      "artistId": "1cNPXWhKfjI0fT5EMCnamR",
      "trackName": "Coro Tá Comendo e Ninguém Tá Vendo",
      "trackId": "3iuajHdMoqzIG4hY9TFNEv",
      "total": 503929,
      "daily": 70
    },
    {
      "artist": "Dj Guuga",
      "artistId": "1cNPXWhKfjI0fT5EMCnamR",
      "trackName": "Da Palinha",
      "trackId": "6mqQsO8lSKTATVATef52Yg",
      "total": 494586,
      "daily": 92
    },
    {
      "artist": "Dj Guuga",
      "artistId": "1cNPXWhKfjI0fT5EMCnamR",
      "trackName": "Perdendo a Memória",
      "trackId": "6Qu6wBYQIUJpNwVmDU1xZc",
      "total": 477218,
      "daily": 8
    },
    {
      "artist": "Dj Guuga",
      "artistId": "1cNPXWhKfjI0fT5EMCnamR",
      "trackName": "Passa Arrocha Nela",
      "trackId": "46mZkSDhTuYwCl7TbY39Cn",
      "total": 475275,
      "daily": 61
    },
    {
      "artist": "Dj Guuga",
      "artistId": "1cNPXWhKfjI0fT5EMCnamR",
      "trackName": "Quem Fode Fode, Quem Não Fode Sai de Cima",
      "trackId": "2lcDY19KofPPH47ZoIsHbY",
      "total": 469468,
      "daily": 3
    },
    {
      "artist": "Dj Guuga",
      "artistId": "1cNPXWhKfjI0fT5EMCnamR",
      "trackName": "Nois Ta Pesado",
      "trackId": "4lcdGbG4qUAUrsUFVLvDNk",
      "total": 456301,
      "daily": 27
    },
    {
      "artist": "Dj Guuga",
      "artistId": "1cNPXWhKfjI0fT5EMCnamR",
      "trackName": "Elas Tão Caindo Na Porrada",
      "trackId": "3ndBusHYN2eyFCN1OaoyXC",
      "total": 433706,
      "daily": 68
    },
    {
      "artist": "Dj Guuga",
      "artistId": "1cNPXWhKfjI0fT5EMCnamR",
      "trackName": "Se Vacilar Vai Ficar Careca",
      "trackId": "3yG3nsSUNSIIDVE95vX3sV",
      "total": 426354,
      "daily": ""
    },
    {
      "artist": "Dj Guuga",
      "artistId": "1cNPXWhKfjI0fT5EMCnamR",
      "trackName": "Vem Sem Medo - Aproveita Que Nóis Ta Solteiro",
      "trackId": "7r4eCzU8sJwbsR9dy9qwou",
      "total": 413151,
      "daily": 2099
    },
    {
      "artist": "Dj Guuga",
      "artistId": "1cNPXWhKfjI0fT5EMCnamR",
      "trackName": "Ninguém Segura Essa Menina",
      "trackId": "1ccJMW8yhFIIvPjthYdHx0",
      "total": 411557,
      "daily": 2
    },
    {
      "artist": "Dj Guuga",
      "artistId": "1cNPXWhKfjI0fT5EMCnamR",
      "trackName": "Met Met Na 17",
      "trackId": "3UvoCoySu4TmJarAuOQ3vm",
      "total": 404213,
      "daily": 14
    },
    {
      "artist": "Dj Guuga",
      "artistId": "1cNPXWhKfjI0fT5EMCnamR",
      "trackName": "Eu Não Saio da Sua Mente",
      "trackId": "0nh0z5QnDeiBG1LyPCHUvL",
      "total": 401574,
      "daily": 301
    },
    {
      "artist": "Dj Guuga",
      "artistId": "1cNPXWhKfjI0fT5EMCnamR",
      "trackName": "Muito Loco de Bala",
      "trackId": "1xKxj3IIa1Kb8ST1qdcNfR",
      "total": 393295,
      "daily": 67
    },
    {
      "artist": "Dj Guuga",
      "artistId": "1cNPXWhKfjI0fT5EMCnamR",
      "trackName": "Vivendo a vida",
      "trackId": "4ajE3ZayS1a2qLNKaBRMdT",
      "total": 386676,
      "daily": 727
    },
    {
      "artist": "Dj Guuga",
      "artistId": "1cNPXWhKfjI0fT5EMCnamR",
      "trackName": "A Novinha Ta Com 5 Namorados",
      "trackId": "4aFgrsVoidC8WsITYQLQ52",
      "total": 382494,
      "daily": 42
    },
    {
      "artist": "Dj Guuga",
      "artistId": "1cNPXWhKfjI0fT5EMCnamR",
      "trackName": "Promoção Pras Fãs",
      "trackId": "5FWNmXPBj811tMjezkJxym",
      "total": 370659,
      "daily": 3
    },
    {
      "artist": "Dj Guuga",
      "artistId": "1cNPXWhKfjI0fT5EMCnamR",
      "trackName": "Vamos Juntar As Brisa e Comer Essas Piranhas",
      "trackId": "3Gkzqg5cSUvbD3WO2sD5G0",
      "total": 369045,
      "daily": 46
    },
    {
      "artist": "Dj Guuga",
      "artistId": "1cNPXWhKfjI0fT5EMCnamR",
      "trackName": "Briguei Com a Namorada",
      "trackId": "5wbbAubK9U9q7tZL7zsS91",
      "total": 349270,
      "daily": 4
    },
    {
      "artist": "Dj Guuga",
      "artistId": "1cNPXWhKfjI0fT5EMCnamR",
      "trackName": "Sentada Maliciosa",
      "trackId": "4ZbkaBV5Ju3R8VesqjDZWh",
      "total": 348852,
      "daily": 10
    },
    {
      "artist": "Dj Guuga",
      "artistId": "1cNPXWhKfjI0fT5EMCnamR",
      "trackName": "Os Muleke é Foda",
      "trackId": "79Grl8LIQKhWRqpPmyqVZz",
      "total": 342235,
      "daily": 34
    },
    {
      "artist": "Dj Guuga",
      "artistId": "1cNPXWhKfjI0fT5EMCnamR",
      "trackName": "Mostra O Que Ele Perdeu",
      "trackId": "797aeU0Bny1pnYoVKRcIQt",
      "total": 337458,
      "daily": 44
    },
    {
      "artist": "Dj Guuga",
      "artistId": "1cNPXWhKfjI0fT5EMCnamR",
      "trackName": "Sextou",
      "trackId": "6smq1E5uhr9WIXUpJuEo5J",
      "total": 331683,
      "daily": 33
    },
    {
      "artist": "Dj Guuga",
      "artistId": "1cNPXWhKfjI0fT5EMCnamR",
      "trackName": "ACOMPANHA O PONTINHO",
      "trackId": "6LUPZhkHNqcIkgKznFQBBd",
      "total": 328982,
      "daily": 3878
    },
    {
      "artist": "Dj Guuga",
      "artistId": "1cNPXWhKfjI0fT5EMCnamR",
      "trackName": "Quis Terminar",
      "trackId": "0b3JfktU2yRoJIH791gvPZ",
      "total": 318624,
      "daily": 127
    },
    {
      "artist": "Dj Guuga",
      "artistId": "1cNPXWhKfjI0fT5EMCnamR",
      "trackName": "Assume Aí",
      "trackId": "4ZT3WQnghsvyJm58N0St9H",
      "total": 311310,
      "daily": 4
    },
    {
      "artist": "Dj Guuga",
      "artistId": "1cNPXWhKfjI0fT5EMCnamR",
      "trackName": "Se Lambuzando",
      "trackId": "3Oq7PkstN5yl4N8T2o6kLl",
      "total": 309241,
      "daily": 29
    },
    {
      "artist": "Dj Guuga",
      "artistId": "1cNPXWhKfjI0fT5EMCnamR",
      "trackName": "Ela Tira Onda com Sua Cara",
      "trackId": "0HxKhsuyIp7WgWyb17Fbax",
      "total": 303263,
      "daily": 3
    },
    {
      "artist": "Dj Guuga",
      "artistId": "1cNPXWhKfjI0fT5EMCnamR",
      "trackName": "Fique em Casa",
      "trackId": "78yf6Y0xr99Q3ZaS9uRrwo",
      "total": 296962,
      "daily": 23
    },
    {
      "artist": "Dj Guuga",
      "artistId": "1cNPXWhKfjI0fT5EMCnamR",
      "trackName": "Dia de Bater a Gilete no Box",
      "trackId": "5MAoUzvZXSXTkiaG41rQVn",
      "total": 293904,
      "daily": 14
    },
    {
      "artist": "Dj Guuga",
      "artistId": "1cNPXWhKfjI0fT5EMCnamR",
      "trackName": "On Pra Rolê Off Pra Romance",
      "trackId": "6oyokhwnUhRtgjvmfJBIaG",
      "total": 291465,
      "daily": 867
    },
    {
      "artist": "Dj Guuga",
      "artistId": "1cNPXWhKfjI0fT5EMCnamR",
      "trackName": "Deixa em off",
      "trackId": "7ezBfhfsvDX6eZcFNzHfp7",
      "total": 283449,
      "daily": 1171
    },
    {
      "artist": "Dj Guuga",
      "artistId": "1cNPXWhKfjI0fT5EMCnamR",
      "trackName": "Lapada de Saudades",
      "trackId": "3z2IocX55CZdpDd34oEQtk",
      "total": 278801,
      "daily": 6
    },
    {
      "artist": "Dj Guuga",
      "artistId": "1cNPXWhKfjI0fT5EMCnamR",
      "trackName": "To a Milhão",
      "trackId": "07h0GGCaQcJZL5OcuHA5LR",
      "total": 263636,
      "daily": 40
    },
    {
      "artist": "Dj Guuga",
      "artistId": "1cNPXWhKfjI0fT5EMCnamR",
      "trackName": "Fedidinha",
      "trackId": "0PcGZgddNUJzNCf9B1pFws",
      "total": 263013,
      "daily": 19
    },
    {
      "artist": "Dj Guuga",
      "artistId": "1cNPXWhKfjI0fT5EMCnamR",
      "trackName": "Você Que Lute Pra me Superar",
      "trackId": "23qxa0QxKLtiMHdopJECXW",
      "total": 261019,
      "daily": 11
    },
    {
      "artist": "Dj Guuga",
      "artistId": "1cNPXWhKfjI0fT5EMCnamR",
      "trackName": "Fama de Golpista",
      "trackId": "27p84A9AaKawzmQ6kOJBOg",
      "total": 257739,
      "daily": 22
    },
    {
      "artist": "Dj Guuga",
      "artistId": "1cNPXWhKfjI0fT5EMCnamR",
      "trackName": "Não Sufoque o Artista",
      "trackId": "1Dmfh3Dxc5vund8ljwsg8U",
      "total": 256799,
      "daily": 190
    },
    {
      "artist": "Dj Guuga",
      "artistId": "1cNPXWhKfjI0fT5EMCnamR",
      "trackName": "Tropa da G R 6 - DJ Guuga Mix",
      "trackId": "48PICS6dWrylkgvd3eKlyt",
      "total": 251114,
      "daily": 1
    },
    {
      "artist": "Dj Guuga",
      "artistId": "1cNPXWhKfjI0fT5EMCnamR",
      "trackName": "Joga Polpa",
      "trackId": "1l31ZxmoXmfqCXPRO8kLxu",
      "total": 242262,
      "daily": 7
    },
    {
      "artist": "Dj Guuga",
      "artistId": "1cNPXWhKfjI0fT5EMCnamR",
      "trackName": "Vai da Pra Malandro",
      "trackId": "1VmQcXhUHufWk4HlDfPlL1",
      "total": 241135,
      "daily": 13
    },
    {
      "artist": "Dj Guuga",
      "artistId": "1cNPXWhKfjI0fT5EMCnamR",
      "trackName": "Rave The Book Is On The Table",
      "trackId": "1KDEPPoWznnxM1k8oTlSBc",
      "total": 238858,
      "daily": 40
    },
    {
      "artist": "Dj Guuga",
      "artistId": "1cNPXWhKfjI0fT5EMCnamR",
      "trackName": "Vucudão",
      "trackId": "4IDtOkUI7m2yOw2H6fXU1W",
      "total": 236356,
      "daily": 10
    },
    {
      "artist": "Dj Guuga",
      "artistId": "1cNPXWhKfjI0fT5EMCnamR",
      "trackName": "Só Colocada Com Força",
      "trackId": "0MZZyGWNvdEBlrJnV2vmpH",
      "total": 231414,
      "daily": 4
    },
    {
      "artist": "Dj Guuga",
      "artistId": "1cNPXWhKfjI0fT5EMCnamR",
      "trackName": "Minha namorada descobriu que sou casado",
      "trackId": "77xu14f5MeNly0Bhxk6TTB",
      "total": 228905,
      "daily": 469
    },
    {
      "artist": "Dj Guuga",
      "artistId": "1cNPXWhKfjI0fT5EMCnamR",
      "trackName": "Sou inamorável",
      "trackId": "5Jc7lqcxc51blPn9ljzDUt",
      "total": 225940,
      "daily": 245
    },
    {
      "artist": "Dj Guuga",
      "artistId": "1cNPXWhKfjI0fT5EMCnamR",
      "trackName": "Foda-Se Se Eu Fumo",
      "trackId": "1mQKaZiFBCZLsbMmCE4u9e",
      "total": 215320,
      "daily": 10
    },
    {
      "artist": "Dj Guuga",
      "artistId": "1cNPXWhKfjI0fT5EMCnamR",
      "trackName": "Combate",
      "trackId": "0HEWVIvjzaSdUiEabGufgn",
      "total": 212406,
      "daily": 477
    },
    {
      "artist": "Dj Guuga",
      "artistId": "1cNPXWhKfjI0fT5EMCnamR",
      "trackName": "Tu Vai Vê o Que É Sofrer",
      "trackId": "7LdSGCKVWM9eq5dQ3HT5L5",
      "total": 212064,
      "daily": 5
    },
    {
      "artist": "Dj Guuga",
      "artistId": "1cNPXWhKfjI0fT5EMCnamR",
      "trackName": "Catucada (Ela Tá Querendo E Não Tá Sebendo Pedir)",
      "trackId": "7DTB3YYBD5iwcQEG1O1gzv",
      "total": 210866,
      "daily": 327
    },
    {
      "artist": "Dj Guuga",
      "artistId": "1cNPXWhKfjI0fT5EMCnamR",
      "trackName": "Não Me Liga",
      "trackId": "3be2w6pW1NcmVKlx2cDYbp",
      "total": 201213,
      "daily": 46
    },
    {
      "artist": "Dj Guuga",
      "artistId": "1cNPXWhKfjI0fT5EMCnamR",
      "trackName": "Então Vai Bucetão No Chão",
      "trackId": "3x7aiV5ypyp6QXyIaZSesT",
      "total": 197730,
      "daily": 9
    },
    {
      "artist": "Dj Guuga",
      "artistId": "1cNPXWhKfjI0fT5EMCnamR",
      "trackName": "Ela Ta Me Hipnotizando",
      "trackId": "3hdvH8rppIfa46mcIuhtuA",
      "total": 184957,
      "daily": 6
    },
    {
      "artist": "Dj Guuga",
      "artistId": "1cNPXWhKfjI0fT5EMCnamR",
      "trackName": "Pitbull de Raça",
      "trackId": "7BtWbrQemfuYKiGtikIMcQ",
      "total": 182317,
      "daily": 2
    },
    {
      "artist": "Dj Guuga",
      "artistId": "1cNPXWhKfjI0fT5EMCnamR",
      "trackName": "CORNETEIRA DAS GOSTOSAS",
      "trackId": "2SXZEJPag6wdcZ8RE41jkf",
      "total": 178565,
      "daily": 1267
    },
    {
      "artist": "Dj Guuga",
      "artistId": "1cNPXWhKfjI0fT5EMCnamR",
      "trackName": "Passa a Buceta Nele",
      "trackId": "3lI8KwEOq4QNOHS1giR8x6",
      "total": 176666,
      "daily": 16
    },
    {
      "artist": "Dj Guuga",
      "artistId": "1cNPXWhKfjI0fT5EMCnamR",
      "trackName": "Botada Botada",
      "trackId": "2gscNBU79GFPUipE0B56mb",
      "total": 174353,
      "daily": 327
    },
    {
      "artist": "Dj Guuga",
      "artistId": "1cNPXWhKfjI0fT5EMCnamR",
      "trackName": "Meia-Noite de Ano Novo",
      "trackId": "0XRmXn5bBAgKIQ7bfhoZZe",
      "total": 172778,
      "daily": 22
    },
    {
      "artist": "Dj Guuga",
      "artistId": "1cNPXWhKfjI0fT5EMCnamR",
      "trackName": "Mágica",
      "trackId": "2lNMNM8ajqPFu74NHXPzHy",
      "total": 168977,
      "daily": 66
    },
    {
      "artist": "Dj Guuga",
      "artistId": "1cNPXWhKfjI0fT5EMCnamR",
      "trackName": "Foda-se o Amor",
      "trackId": "6fSrQdhpNEI6yhl9w4zcD1",
      "total": 165523,
      "daily": 56
    },
    {
      "artist": "Dj Guuga",
      "artistId": "1cNPXWhKfjI0fT5EMCnamR",
      "trackName": "Nudezinho",
      "trackId": "1cIRW8SnAWwB3Ln6NXXKgC",
      "total": 165223,
      "daily": 11
    },
    {
      "artist": "Dj Guuga",
      "artistId": "1cNPXWhKfjI0fT5EMCnamR",
      "trackName": "Com Ciúmes é Mais Caro",
      "trackId": "5GzJDQOBczBeIfaJ0MUzOz",
      "total": 163098,
      "daily": 302
    },
    {
      "artist": "Dj Guuga",
      "artistId": "1cNPXWhKfjI0fT5EMCnamR",
      "trackName": "Montagem (Pode Pode Pode) Posso Botar na Sua Garagem",
      "trackId": "76nSqep7aaJ3oKPuVw6kH0",
      "total": 162052,
      "daily": 276
    },
    {
      "artist": "Dj Guuga",
      "artistId": "1cNPXWhKfjI0fT5EMCnamR",
      "trackName": "Sextou Vou Cair na Bagaceira",
      "trackId": "0cUfrwp8akFqUIM2mbScFM",
      "total": 154830,
      "daily": 205
    },
    {
      "artist": "Dj Guuga",
      "artistId": "1cNPXWhKfjI0fT5EMCnamR",
      "trackName": "Parabéns",
      "trackId": "2mxdffSmSxRHdC6qVSxUAw",
      "total": 152839,
      "daily": 102
    },
    {
      "artist": "Dj Guuga",
      "artistId": "1cNPXWhKfjI0fT5EMCnamR",
      "trackName": "Tô Comendo Outra Mais Gostosa que Você",
      "trackId": "6d3TPdm9yoZGJxsS00NzEn",
      "total": 139210,
      "daily": 24
    },
    {
      "artist": "Dj Guuga",
      "artistId": "1cNPXWhKfjI0fT5EMCnamR",
      "trackName": "Opção",
      "trackId": "6TLfYBqycrYAzBmSZwakN4",
      "total": 134810,
      "daily": 332
    },
    {
      "artist": "Dj Guuga",
      "artistId": "1cNPXWhKfjI0fT5EMCnamR",
      "trackName": "Não vou namorar",
      "trackId": "0B3FXUUmQ3YqHlawwKxsTC",
      "total": 127031,
      "daily": 465
    },
    {
      "artist": "Dj Guuga",
      "artistId": "1cNPXWhKfjI0fT5EMCnamR",
      "trackName": "Saudade Né Minha Filha",
      "trackId": "5Wmh6U1YMMwKH0lfv8kl3c",
      "total": 124164,
      "daily": 37
    },
    {
      "artist": "Dj Guuga",
      "artistId": "1cNPXWhKfjI0fT5EMCnamR",
      "trackName": "Luz Câmera Ação",
      "trackId": "6qg8B2ISh6Lfqa46CJ1fyE",
      "total": 114484,
      "daily": 7
    },
    {
      "artist": "Dj Guuga",
      "artistId": "1cNPXWhKfjI0fT5EMCnamR",
      "trackName": "Acompanha o Grave",
      "trackId": "56LzEj2vjrdGWHShjIurEI",
      "total": 111954,
      "daily": 53
    },
    {
      "artist": "Dj Guuga",
      "artistId": "1cNPXWhKfjI0fT5EMCnamR",
      "trackName": "Empina Empina",
      "trackId": "1R7v62tHVXe1VwXqfq6Es8",
      "total": 111439,
      "daily": 27
    },
    {
      "artist": "Dj Guuga",
      "artistId": "1cNPXWhKfjI0fT5EMCnamR",
      "trackName": "Visão de Milionário",
      "trackId": "0vh3qkX4Pwd6uhc7G1Z6lo",
      "total": 108436,
      "daily": 12
    },
    {
      "artist": "Dj Guuga",
      "artistId": "1cNPXWhKfjI0fT5EMCnamR",
      "trackName": "Vou Pegar Minha Ex",
      "trackId": "4cuIpSa7meycI4SSt7HIV4",
      "total": 106211,
      "daily": 6
    },
    {
      "artist": "Dj Guuga",
      "artistId": "1cNPXWhKfjI0fT5EMCnamR",
      "trackName": "É Amor ou Ódio - Ela Fode Com Meu Psicológico",
      "trackId": "4fPrXZ9uFpSfKCrDI1bWte",
      "total": 102293,
      "daily": 112
    }
  ]
}